cronyo/VERSION
cronyo/__init__.py
cronyo/aws_api.py
cronyo/cli.py
cronyo/config.py
cronyo/config.yml.template
cronyo/cron_rules.py
cronyo/cronyo.py
cronyo/deploy.py
cronyo/logger.py
cronyo/vendor/PyYAML-5.1-py3.7.egg-info/PKG-INFO
cronyo/vendor/PyYAML-5.1-py3.7.egg-info/SOURCES.txt
cronyo/vendor/PyYAML-5.1-py3.7.egg-info/dependency_links.txt
cronyo/vendor/PyYAML-5.1-py3.7.egg-info/installed-files.txt
cronyo/vendor/PyYAML-5.1-py3.7.egg-info/top_level.txt
cronyo/vendor/bin/chardetect
cronyo/vendor/certifi/__init__.py
cronyo/vendor/certifi/__main__.py
cronyo/vendor/certifi/cacert.pem
cronyo/vendor/certifi/core.py
cronyo/vendor/certifi/__pycache__/__init__.cpython-37.pyc
cronyo/vendor/certifi/__pycache__/__init__.cpython-38.pyc
cronyo/vendor/certifi/__pycache__/__main__.cpython-37.pyc
cronyo/vendor/certifi/__pycache__/core.cpython-37.pyc
cronyo/vendor/certifi/__pycache__/core.cpython-38.pyc
cronyo/vendor/chardet/__init__.py
cronyo/vendor/chardet/big5freq.py
cronyo/vendor/chardet/big5prober.py
cronyo/vendor/chardet/chardistribution.py
cronyo/vendor/chardet/charsetgroupprober.py
cronyo/vendor/chardet/charsetprober.py
cronyo/vendor/chardet/codingstatemachine.py
cronyo/vendor/chardet/compat.py
cronyo/vendor/chardet/cp949prober.py
cronyo/vendor/chardet/enums.py
cronyo/vendor/chardet/escprober.py
cronyo/vendor/chardet/escsm.py
cronyo/vendor/chardet/eucjpprober.py
cronyo/vendor/chardet/euckrfreq.py
cronyo/vendor/chardet/euckrprober.py
cronyo/vendor/chardet/euctwfreq.py
cronyo/vendor/chardet/euctwprober.py
cronyo/vendor/chardet/gb2312freq.py
cronyo/vendor/chardet/gb2312prober.py
cronyo/vendor/chardet/hebrewprober.py
cronyo/vendor/chardet/jisfreq.py
cronyo/vendor/chardet/jpcntx.py
cronyo/vendor/chardet/langbulgarianmodel.py
cronyo/vendor/chardet/langcyrillicmodel.py
cronyo/vendor/chardet/langgreekmodel.py
cronyo/vendor/chardet/langhebrewmodel.py
cronyo/vendor/chardet/langhungarianmodel.py
cronyo/vendor/chardet/langthaimodel.py
cronyo/vendor/chardet/langturkishmodel.py
cronyo/vendor/chardet/latin1prober.py
cronyo/vendor/chardet/mbcharsetprober.py
cronyo/vendor/chardet/mbcsgroupprober.py
cronyo/vendor/chardet/mbcssm.py
cronyo/vendor/chardet/sbcharsetprober.py
cronyo/vendor/chardet/sbcsgroupprober.py
cronyo/vendor/chardet/sjisprober.py
cronyo-0.4.5.dist-info/LICENSE
cronyo-0.4.5.dist-info/METADATA
cronyo-0.4.5.dist-info/WHEEL
cronyo-0.4.5.dist-info/entry_points.txt
cronyo-0.4.5.dist-info/top_level.txt
cronyo/vendor/certifi-2019.9.11.dist-info/DESCRIPTION.rst
cronyo/vendor/certifi-2019.9.11.dist-info/INSTALLER
cronyo/vendor/certifi-2019.9.11.dist-info/METADATA
cronyo/vendor/certifi-2019.9.11.dist-info/RECORD
cronyo/vendor/certifi-2019.9.11.dist-info/WHEEL
cronyo/vendor/certifi-2019.9.11.dist-info/metadata.json
cronyo/vendor/certifi-2019.9.11.dist-info/top_level.txt
cronyo/vendor/chardet-3.0.4.dist-info/DESCRIPTION.rst
cronyo/vendor/chardet-3.0.4.dist-info/INSTALLER
cronyo/vendor/chardet-3.0.4.dist-info/METADATA
cronyo/vendor/chardet-3.0.4.dist-info/RECORD
cronyo/vendor/chardet-3.0.4.dist-info/WHEEL
cronyo/vendor/chardet-3.0.4.dist-info/entry_points.txt
cronyo/vendor/chardet-3.0.4.dist-info/metadata.json
cronyo/vendor/chardet-3.0.4.dist-info/top_level.txt
cronyo/vendor/idna-2.8.dist-info/INSTALLER
cronyo/vendor/idna-2.8.dist-info/LICENSE.rst
cronyo/vendor/idna-2.8.dist-info/METADATA
cronyo/vendor/idna-2.8.dist-info/RECORD
cronyo/vendor/idna-2.8.dist-info/WHEEL
cronyo/vendor/idna-2.8.dist-info/top_level.txt
cronyo/vendor/requests-2.22.0.dist-info/INSTALLER
cronyo/vendor/requests-2.22.0.dist-info/LICENSE
cronyo/vendor/requests-2.22.0.dist-info/METADATA
cronyo/vendor/requests-2.22.0.dist-info/RECORD
cronyo/vendor/requests-2.22.0.dist-info/WHEEL
cronyo/vendor/requests-2.22.0.dist-info/top_level.txt
cronyo/vendor/urllib3-1.25.6.dist-info/INSTALLER
cronyo/vendor/urllib3-1.25.6.dist-info/LICENSE.txt
cronyo/vendor/urllib3-1.25.6.dist-info/METADATA
cronyo/vendor/urllib3-1.25.6.dist-info/RECORD
cronyo/vendor/urllib3-1.25.6.dist-info/WHEEL
cronyo/vendor/urllib3-1.25.6.dist-info/top_level.txt
cronyo-0.4.5.dist-info/RECORD
